{"bio":{"mlb_player_id":683000,"full_name":"Riley Cornelio","birth_date":"2000-06-06","birth_country":"USA","height_inches":75,"weight_lbs":195,"bat_side":"R","pitch_hand":"R","primary_position_code":"1","primary_position_name":"Pitcher","mlb_debut_date":"2026-04-24","last_played_date":null,"active":true},"is_pitcher":true,"career":{"batting":[],"pitching":[{"year":2026,"team_id":"WSN","war":-0.25,"salary":null,"g":1,"gs":0,"era_plus":52.8,"ra":3,"xra":0.884,"bip":7.0}]},"percentiles":{"pitching":[],"batting":[]},"expected":{"batting":[],"pitching":[]},"arsenal":[],"pitch_movement":[],"trades":[],"awards":[],"contracts":[]}