{"bio":{"mlb_player_id":690953,"full_name":"Mick Abel","birth_date":"2001-08-18","birth_country":"USA","height_inches":77,"weight_lbs":190,"bat_side":"R","pitch_hand":"R","primary_position_code":"1","primary_position_name":"Pitcher","mlb_debut_date":"2025-05-18","last_played_date":null,"active":true},"is_pitcher":true,"career":{"batting":[{"year":2025,"team_id":"PHI","war":null,"salary":null,"g":0,"pa":0,"runs_above_avg":0.0,"runs_above_avg_off":0.0,"runs_above_avg_def":0.0}],"pitching":[{"year":2025,"team_id":"MIN","war":-0.44,"salary":null,"g":4,"gs":2,"era_plus":52.2615384615385,"ra":14,"xra":6.716,"bip":41.0},{"year":2025,"team_id":"PHI","war":0.27,"salary":null,"g":6,"gs":6,"era_plus":88.35,"ra":14,"xra":12.68,"bip":77.0},{"year":2026,"team_id":"MIN","war":0.43,"salary":null,"g":4,"gs":3,"era_plus":110.0888888888889,"ra":9,"xra":10.471,"bip":57.0}]},"percentiles":{"pitching":[],"batting":[]},"expected":{"batting":[],"pitching":[]},"arsenal":[],"pitch_movement":[],"trades":[],"awards":[],"contracts":[{"season":2025,"team_bref":"MIN","status":"Pre-Arbitration","service_time":0.05,"acquired_method":"3","base_salary":782500,"cap_hit":782500,"signing_bonus":782500,"position":"SP"}]}