{"bio":{"mlb_player_id":701121,"full_name":"Logan VanWey","birth_date":"1999-02-14","birth_country":"USA","height_inches":74,"weight_lbs":205,"bat_side":"R","pitch_hand":"R","primary_position_code":"1","primary_position_name":"Pitcher","mlb_debut_date":"2025-04-11","last_played_date":null,"active":true},"is_pitcher":true,"career":{"batting":[],"pitching":[{"year":2025,"team_id":"HOU","war":-0.1,"salary":null,"g":9,"gs":0,"era_plus":84.5166666666667,"ra":7,"xra":5.109,"bip":38.0},{"year":2026,"team_id":"HOU","war":0.06,"salary":null,"g":2,"gs":0,"era_plus":null,"ra":0,"xra":0.859,"bip":4.0}]},"percentiles":{"pitching":[],"batting":[]},"expected":{"batting":[],"pitching":[]},"arsenal":[],"pitch_movement":[],"trades":[],"awards":[],"contracts":[]}